lzallright-0.2.6.dist-info/METADATA
lzallright-0.2.6.dist-info/WHEEL
lzallright-0.2.6.dist-info/licenses/LICENSE
lzallright/__init__.py
lzallright/_lzallright.cpython-313t-darwin.so
lzallright/_lzallright.pyi
lzallright/py.typed
lzallright-0.2.6.dist-info/RECORD
