Metadata-Version: 2.4
Name: lzallright
Version: 0.2.6
License-File: LICENSE
Summary: A Python 3.8+ binding for LZ👌(lzokay) library
Home-Page: https://github.com/vlaci/lzallright
Author: László Vaskó <1771332+vlaci@users.noreply.github.com>
Author-email: László Vaskó <1771332+vlaci@users.noreply.github.com>
License: MIT
Requires-Python: >=3.8
Project-URL: Homepage, https://vlaci.github.io/lzallright
Project-URL: Repository, https://github.com/vlaci/lzallright
Project-URL: Changelog, https://github.com/vlaci/lzallright/blob/main/CHANGELOG.md
